{
    "config": {
        "naptanPlatformTags": true
    },
    "routes": {
        "edinburgh_city": [
            {"name": "1", "relation_id": 11702779},
            {"name": "2", "relation_id": 16025554},
            {"name": "3", "relation_id": 11087988},
            {"name": "4", "relation_id": 310090},
            {"name": "5", "relation_id": 16220337},
            {"name": "7", "relation_id": 11221396},
            {"name": "8", "relation_id": 7643291},
            {"name": "9", "relation_id": 16220437},
            {"name": "10", "relation_id": 2190289},
            {"name": "11", "relation_id": 11221362},
            {"name": "12", "relation_id": 10529100},
            {"name": "13", "relation_id": 16348449},
            {"name": "14", "relation_id": 16214073},
            {"name": "15", "relation_id": 16254778},
            {"name": "16", "relation_id": 10529294},
            {"name": "19", "relation_id": 11909907},
            {"name": "20", "relation_id": 16355489},
            {"name": "21", "relation_id": 11146200},
            {"name": "22", "relation_id": 16254896},
            {"name": "23", "relation_id": 5926221},
            {"name": "24", "relation_id": 946201},
            {"name": "25", "relation_id": 7650283},
            {"name": "26", "relation_id": 11074556},
            {"name": "X26", "relation_id": 0},
            {"name": "27", "relation_id": 1358434},
            {"name": "29", "relation_id": 12561097},
            {"name": "X29", "relation_id": 0},
            {"name": "30", "relation_id": 16291449},
            {"name": "31", "relation_id": 7797069},
            {"name": "X31", "relation_id": 0},
            {"name": "33", "relation_id": 16344547},
            {"name": "X33", "relation_id": 0},
            {"name": "34", "relation_id": 15786785},
            {"name": "35", "relation_id": 8593878},
            {"name": "36", "relation_id": 2247597},
            {"name": "37", "relation_id": 11300139},
            {"name": "X37", "relation_id": 0},
            {"name": "38", "relation_id": 16289166},
            {"name": "41", "relation_id": 11014193, "comment": "not listed on Lothian buses"},
            {"name": "44", "relation_id": 11375367},
            {"name": "X44", "relation_id": 0},
            {"name": "45", "relation_id": 16344817},
            {"name": "46", "relation_id": 0},
            {"name": "47", "relation_id": 11245656},
            {"name": "47B", "relation_id": 0},
            {"name": "48", "relation_id": 0},
            {"name": "49", "relation_id": 7654545},
            {"name": "63", "relation_id": 16358697, "comment": "Balerno <=> Queensferry"},
            {"name": "98", "relation_id": 0}
        ],
        "edinburgh_airport": [
            {"name": "100", "relation_id": 11217795},
            {"name": "200", "relation_id": 7261862},
            {"name": "N200", "relation_id": 0},
            {"name": "400", "relation_id": 8631405},
            {"name": "N400", "relation_id": 0}
        ],
        "edinburgh_country": [
            {"name": "43", "relation_id": 11105014},
            {"name": "X18", "relation_id": 0},
            {"name": "X27", "relation_id": 0},
            {"name": "X28", "relation_id": 0}
        ],
        "edinburgh_east_coast": [
            {"name": "X6", "relation_id": 4222037},
            {"name": "X7", "relation_id": 0},
            {"name": "106", "relation_id": 0},
            {"name": "113", "relation_id": 3009058},
            {"name": "124", "relation_id": 10151782},
            {"name": "X5", "relation_id": 10151806},
            {"name": "139", "relation_id": 0},
            {"name": "140", "relation_id": 10613957},
            {"name": "141", "relation_id": 0}
        ],
        "edinburgh_night": [
            {"name": "N3", "relation_id": 0},
            {"name": "N11", "relation_id": 0},
            {"name": "N14", "relation_id": 0},
            {"name": "N16", "relation_id": 0},
            {"name": "N18", "relation_id": 0},
            {"name": "N22", "relation_id": 0},
            {"name": "N25", "relation_id": 0},
            {"name": "N26", "relation_id": 0},
            {"name": "N28", "relation_id": 0},
            {"name": "N30", "relation_id": 0},
            {"name": "N31", "relation_id": 0},
            {"name": "N37", "relation_id": 0},
            {"name": "N43", "relation_id": 0},
            {"name": "N44", "relation_id": 0},
            {"name": "N107", "relation_id": 0},
            {"name": "N113", "relation_id": 0},
            {"name": "N124", "relation_id": 0}
        ],
        "borders_buses": [
            {"name": "51", "relation_id": 13308277},
            {"name": "52", "relation_id": 0},
            {"name": "253", "relation_id": 0},
            {"name": "X62", "relation_id": 14722579},
            {"name": "X70", "relation_id": 0},
            {"name": "X95", "relation_id": 15017105}
        ],
        "stagecoach_east_scotland": [
            {"name": "X52", "relation_id": 16314703}
        ]
    }
}
